smartcli/__init__.py
smartcli/cli.py
smartcli/exceptions.py
smartcli/modeManager.py
smartcli/nodes/__init__.py
smartcli/nodes/cli_elements.py
smartcli/nodes/interfaces.py
smartcli/nodes/smartList.py
smartcli-0.1.6.dist-info/LICENSE
smartcli-0.1.6.dist-info/METADATA
smartcli-0.1.6.dist-info/WHEEL
smartcli-0.1.6.dist-info/top_level.txt
smartcli-0.1.6.dist-info/RECORD
