Metadata-Version: 2.1
Name: smartcli
Version: 0.1.6
Summary: Cli with a lot of additional functionalities
Author: ProxPxD (Piotr Maliszewski)
Keywords: python,cli,parser,smart,smartcli,smartparser
License-File: LICENSE
